featurecrop/__init__.py
featurecrop-0.0.1.dist-info/LICENSE
featurecrop-0.0.1.dist-info/METADATA
featurecrop-0.0.1.dist-info/WHEEL
featurecrop-0.0.1.dist-info/top_level.txt
featurecrop-0.0.1.dist-info/RECORD
