Metadata-Version: 2.1
Name: featurecrop
Version: 0.0.1
Summary: FeatureCrop is a Python library designed to automatically crop an image
Home-page: https://github.com/manbehindthemadness/featurecrop
Author: Manbehindthemadness
Author-email: manbehindthemadness@gmail.com
Classifier: Programming Language :: Python :: 3
Classifier: License :: OSI Approved :: Apache Software License
Classifier: Operating System :: OS Independent
Requires-Python: >=3.10
License-File: LICENSE
Requires-Dist: numpy
Requires-Dist: opencv-python
